cka_analyzer/__init__.py
cka_analyzer/cli.py
cka_analyzer/compute.py
cka_analyzer/config.py
cka_analyzer/data.py
cka_analyzer/interface.py
cka_analyzer/model.py
cka_analyzer/plot.py
cka_analyzer-0.1.2.dist-info/METADATA
cka_analyzer-0.1.2.dist-info/WHEEL
cka_analyzer-0.1.2.dist-info/entry_points.txt
cka_analyzer-0.1.2.dist-info/top_level.txt
cka_analyzer-0.1.2.dist-info/RECORD
